<?xml version="1.0" encoding="utf-8" ?>
<dwsync>
<file name="style.css" server="C:/xampp/htdocs/aso/" local="129737722833003458" remote="129737722830000000" />
<file name="style.css" server="C:/xampp/htdocs/shopatlondon/" local="129977242368302743" remote="129977242360000000" />
<file name="grid.css" server="C:/xampp/htdocs/shopatlondon/" local="129976611951449000" remote="129976611950000000" />
<file name="style.css" server="C:/xampp/htdocs/cooperative/" local="130056995026525095" remote="130056995020000000" />
<file name="grid.css" server="C:/xampp/htdocs/cooperative/" local="129976611951449000" remote="129976611950000000" />
<file name="style.css" server="C:/xampp/htdocs/nimet/" local="130061320010343857" remote="130061320010000000" />
<file name="grid.css" server="C:/xampp/htdocs/nimet/" local="129976611951449000" remote="129976611950000000" />
<file name="style.css" server="C:/xampp/htdocs/nigerco/" local="130064793109096867" remote="130064793100000000" />
</dwsync>